rpg_e/__init__.py
rpg_e/game.py
rpg_e/test.py
rpg_e-1.0.0.dist-info/METADATA
rpg_e-1.0.0.dist-info/WHEEL
rpg_e-1.0.0.dist-info/RECORD
