Metadata-Version: 2.1
Name: rpg-e
Version: 1.0.0
Summary: 
Author: Ethan Illingsworth
Author-email: illingsworth.ethan@gmail.com
Requires-Python: >=3.11,<4.0
Classifier: Programming Language :: Python :: 3
Classifier: Programming Language :: Python :: 3.11
Classifier: Programming Language :: Python :: 3.12
Requires-Dist: colorama (>=0.4.6,<0.5.0)
